{
  "cts" : 1767956999945,
  "name" : "TEST_TBAC_NODES",
  "exportedBy" : "Kiran Kamble",
  "data" : [ {
    "type" : "proxy",
    "collectionName" : "ApiBuilder.Proxy.List",
    "data" : {
      "proxyData" : {
        "id" : "6960cee9867f997c2000886a",
        "cts" : 1767952105628,
        "createdUserName" : "Kiran Kamble",
        "modifiedUserName" : "Kiran Kamble",
        "mts" : 1767956999790,
        "createdBy" : "685b8a3df073051941d15c1c",
        "modifiedBy" : "685b8a3df073051941d15c1c",
        "taggedTeams" : [ ],
        "proxyId" : "6960cee9867f997c20008869",
        "revision" : 1,
        "name" : "TEST_TBAC_NODES",
        "description" : "",
        "apiType" : "RESTAPI",
        "apiMethod" : "GET",
        "path" : "/testtbacnodes",
        "pathArray" : [ "testtbacnodes" ],
        "revisionStatus" : "REVIEW",
        "locked" : true,
        "lockedBy" : "Kiran Kamble",
        "nodeDataHashMap" : {
          "inbound" : {
            "e5a0bb76-5e29-4a2c-8f0b-2ea9a582eb25" : [ "v1" ],
            "1644b62d-e8eb-44b3-b785-7c4184128104" : [ "e5a0bb76-5e29-4a2c-8f0b-2ea9a582eb25" ],
            "ceb27528-fda8-482f-a3eb-6282c120ae78" : [ "1644b62d-e8eb-44b3-b785-7c4184128104" ],
            "a1b54789-71fd-4b55-b7ad-b86e46297ede" : [ "164f08ce-aeab-4785-90dd-35d623d5e923" ],
            "6d911907-26f4-493f-ab1f-6f969085dcb3" : [ "879832e5-5695-41b5-996a-3ff373f6544c" ],
            "879832e5-5695-41b5-996a-3ff373f6544c" : [ "a1b54789-71fd-4b55-b7ad-b86e46297ede" ],
            "164f08ce-aeab-4785-90dd-35d623d5e923" : [ "ceb27528-fda8-482f-a3eb-6282c120ae78" ],
            "6fe55857-41c8-4da2-be73-c026cd699239" : [ "ceb27528-fda8-482f-a3eb-6282c120ae78" ]
          },
          "outbound" : {
            "v1" : [ "e5a0bb76-5e29-4a2c-8f0b-2ea9a582eb25" ],
            "e5a0bb76-5e29-4a2c-8f0b-2ea9a582eb25" : [ "1644b62d-e8eb-44b3-b785-7c4184128104" ],
            "1644b62d-e8eb-44b3-b785-7c4184128104" : [ "ceb27528-fda8-482f-a3eb-6282c120ae78" ],
            "164f08ce-aeab-4785-90dd-35d623d5e923" : [ "a1b54789-71fd-4b55-b7ad-b86e46297ede" ],
            "879832e5-5695-41b5-996a-3ff373f6544c" : [ "6d911907-26f4-493f-ab1f-6f969085dcb3" ],
            "a1b54789-71fd-4b55-b7ad-b86e46297ede" : [ "879832e5-5695-41b5-996a-3ff373f6544c" ],
            "ceb27528-fda8-482f-a3eb-6282c120ae78" : [ "6fe55857-41c8-4da2-be73-c026cd699239", "164f08ce-aeab-4785-90dd-35d623d5e923" ]
          },
          "allNeighbours" : [ "879832e5-5695-41b5-996a-3ff373f6544c", "6fe55857-41c8-4da2-be73-c026cd699239", "164f08ce-aeab-4785-90dd-35d623d5e923", "a1b54789-71fd-4b55-b7ad-b86e46297ede", "6d911907-26f4-493f-ab1f-6f969085dcb3", "v1", "1644b62d-e8eb-44b3-b785-7c4184128104", "ceb27528-fda8-482f-a3eb-6282c120ae78", "e5a0bb76-5e29-4a2c-8f0b-2ea9a582eb25" ]
        },
        "vertexHashMap" : {
          "879832e5-5695-41b5-996a-3ff373f6544c" : {
            "vertexId" : "879832e5-5695-41b5-996a-3ff373f6544c",
            "vertexType" : "CALL_WORKFLOW",
            "name" : "Call Workflow",
            "description" : "",
            "callWorkflowData" : {
              "childWorkflowId" : "6960939f613749329516d1e7",
              "childWorkflowName" : "New Workflow 847",
              "virtualHostId" : "66dc0ef2e836d076001b628b",
              "virtualHostName" : "stage-data",
              "url" : "HTTPS://stage-data-lkgc.apiwiz.io/ParentFlow",
              "apiMethod" : "GET",
              "request" : {
                "headerParams" : [ ],
                "queryParams" : [ ],
                "targetRequestBodyType" : "NONE",
                "body" : {
                  "data" : "{}",
                  "type" : "json"
                },
                "formParams" : [ ],
                "urlEncodedParams" : [ ]
              },
              "response" : {
                "statusCode" : 400,
                "variables" : [ ]
              },
              "timeout" : 0,
              "skip" : false,
              "showActualErrorMessage" : false,
              "continueOnError" : false,
              "errorResponse" : {
                "statusCode" : 400,
                "body" : {
                  "data" : "",
                  "type" : "json"
                }
              }
            },
            "imported" : false,
            "skipRuntimeVariables" : false
          },
          "6fe55857-41c8-4da2-be73-c026cd699239" : {
            "vertexId" : "6fe55857-41c8-4da2-be73-c026cd699239",
            "vertexType" : "STOP",
            "name" : "Stop",
            "imported" : false,
            "skipRuntimeVariables" : false,
            "proxyResponse" : {
              "statusCode" : 200,
              "body" : {
                "data" : "Failed",
                "type" : "JSON"
              }
            }
          },
          "164f08ce-aeab-4785-90dd-35d623d5e923" : {
            "vertexId" : "164f08ce-aeab-4785-90dd-35d623d5e923",
            "vertexType" : "DATABASE",
            "name" : "testDb",
            "databaseData" : {
              "connectorId" : "6943e47fd4167432fe664f26",
              "databaseType" : "MONGODB",
              "query" : "{\"operation\":\"insert\",\"databaseName\":\"student-details\",\"collection\":\"student.details\",\"documents\":[{\"_id\":\"\",\"name\":\"\",\"age\":\"\",\"class\":\"\",\"roll no\":\"\"}],\"updates\":[{\"q\":{},\"u\":{},\"upsert\":false,\"multi\":false}],\"pipelines\":[{\"$match\":{\"status\":\"TESTED\"}},{\"$facet\":{\"deploymentFacet\":[{\"$group\":{\"_id\":\"$deploymentAccess.name\",\"count\":{\"$sum\":1}}},{\"$sort\":{\"count\":-1}},{\"$limit\":5}],\"tlsSettingsFacet\":[{\"$group\":{\"_id\":\"$tlsSettings.tlsMode\",\"totalCertificates\":{\"$sum\":1},\"avgPort\":{\"$avg\":\"$port\"}}}],\"statusHistoryFacet\":[{\"$unwind\":\"$statusHistory\"},{\"$group\":{\"_id\":\"$statusHistory.status\",\"count\":{\"$sum\":1}}}]}},{\"$project\":{\"deploymentFacet\":1,\"tlsSettingsFacet\":1,\"statusHistoryFacet\":1}}],\"deletes\":[{\"q\":{},\"limit\":0}],\"filter\":{},\"projection\":{},\"sort\":{},\"limit\":0,\"skip\":0}",
              "variableName" : "kk",
              "connectorName" : "Deepak CloudDB Tagged",
              "tenantName" : "student-details",
              "collectionName" : "student.details",
              "manual" : false,
              "skip" : false,
              "showActualErrorMessage" : false,
              "continueOnError" : false,
              "errorResponse" : {
                "statusCode" : 400,
                "body" : {
                  "data" : "",
                  "type" : "json"
                }
              }
            },
            "imported" : false,
            "skipRuntimeVariables" : false
          },
          "a1b54789-71fd-4b55-b7ad-b86e46297ede" : {
            "vertexId" : "a1b54789-71fd-4b55-b7ad-b86e46297ede",
            "vertexType" : "SHARED_FLOW",
            "name" : "TestNode",
            "description" : "",
            "sharedFlowNodeData" : {
              "sharedFlowId" : "6960d2e5867f997c20008afb",
              "sharedFlowName" : "TEST_NODE",
              "inputVariablesMap" : { },
              "importOutputVariables" : false,
              "importedVariables" : [ ],
              "skip" : false,
              "showActualErrorMessage" : false,
              "continueOnError" : false,
              "errorResponse" : {
                "statusCode" : 400,
                "body" : {
                  "data" : "",
                  "type" : "json"
                }
              }
            },
            "imported" : false,
            "skipRuntimeVariables" : false
          },
          "v1" : {
            "vertexId" : "v1",
            "vertexType" : "START",
            "name" : "Request",
            "requestVariables" : [ ],
            "mandatoryHeaders" : [ ],
            "mandatoryQueryParams" : [ ],
            "imported" : true,
            "skipRuntimeVariables" : false,
            "securityResponse" : {
              "isEnabled" : false,
              "skip" : false,
              "showActualErrorMessage" : false,
              "continueOnError" : false,
              "errorResponse" : {
                "statusCode" : 400,
                "body" : {
                  "data" : "",
                  "type" : "json"
                }
              }
            }
          },
          "6d911907-26f4-493f-ab1f-6f969085dcb3" : {
            "vertexId" : "6d911907-26f4-493f-ab1f-6f969085dcb3",
            "vertexType" : "STOP",
            "name" : "Stop",
            "imported" : false,
            "skipRuntimeVariables" : false,
            "proxyResponse" : {
              "statusCode" : 200,
              "headers" : {
                "content-type" : "application/json"
              },
              "body" : {
                "data" : "{\n    \"db\":{{kk}},\n    \"data\":{{data}}\n}",
                "type" : "json"
              }
            }
          },
          "ceb27528-fda8-482f-a3eb-6282c120ae78" : {
            "vertexId" : "ceb27528-fda8-482f-a3eb-6282c120ae78",
            "vertexType" : "CONDITIONAL_FLOW",
            "name" : "Condition",
            "conditionalFlow" : [ {
              "condition" : "if",
              "assertion" : {
                "expression" : "({0})",
                "placeHolders" : [ {
                  "rule" : "EQUAL_TO",
                  "key" : "data",
                  "value" : "postman-echo.com",
                  "valueDataType" : "STRING"
                } ],
                "feelExpression" : false,
                "skip" : false,
                "showActualErrorMessage" : false,
                "continueOnError" : false,
                "errorResponse" : {
                  "statusCode" : 400,
                  "body" : {
                    "data" : "",
                    "type" : "json"
                  }
                }
              },
              "flowVertexes" : [ "164f08ce-aeab-4785-90dd-35d623d5e923" ]
            }, {
              "condition" : "else",
              "assertion" : {
                "feelExpression" : false,
                "skip" : false,
                "showActualErrorMessage" : false,
                "continueOnError" : false
              },
              "flowVertexes" : [ "6fe55857-41c8-4da2-be73-c026cd699239" ]
            } ],
            "imported" : false,
            "skipRuntimeVariables" : false
          },
          "1644b62d-e8eb-44b3-b785-7c4184128104" : {
            "vertexId" : "1644b62d-e8eb-44b3-b785-7c4184128104",
            "vertexType" : "DELAY",
            "name" : "Delay",
            "delayData" : {
              "delayUnit" : "SECONDS",
              "delayAmount" : 2,
              "skip" : false,
              "showActualErrorMessage" : false
            },
            "imported" : false,
            "skipRuntimeVariables" : false
          },
          "e5a0bb76-5e29-4a2c-8f0b-2ea9a582eb25" : {
            "vertexId" : "e5a0bb76-5e29-4a2c-8f0b-2ea9a582eb25",
            "vertexType" : "TARGET",
            "name" : "Testapi",
            "target" : {
              "name" : "Testapi",
              "apiType" : "RESTAPI",
              "request" : {
                "apiMethod" : "GET",
                "scheme" : "https",
                "host" : "postman-echo.com",
                "path" : "/get",
                "headerParams" : [ {
                  "name" : "h",
                  "value" : "123"
                } ],
                "queryParams" : [ {
                  "name" : "q",
                  "value" : "234"
                } ],
                "targetRequestBodyType" : "NONE",
                "body" : {
                  "type" : "json"
                },
                "formParams" : [ ],
                "urlEncodedParams" : [ ]
              },
              "response" : {
                "statusCode" : 400,
                "variables" : [ {
                  "name" : "data",
                  "reference" : "body",
                  "value" : "$.headers.host",
                  "active" : true,
                  "source" : "raw",
                  "hide" : false,
                  "feelExpression" : false
                } ]
              },
              "timeout" : 0,
              "skip" : false,
              "showActualErrorMessage" : false,
              "continueOnError" : false,
              "errorResponse" : {
                "statusCode" : 400,
                "body" : {
                  "data" : "",
                  "type" : "json"
                }
              },
              "securityResponse" : {
                "isEnabled" : false,
                "useEnforcedRules" : false,
                "skip" : false,
                "showActualErrorMessage" : false,
                "continueOnError" : false,
                "errorResponse" : {
                  "statusCode" : 400,
                  "body" : {
                    "data" : "",
                    "type" : "json"
                  }
                }
              }
            },
            "imported" : false,
            "skipRuntimeVariables" : false
          }
        },
        "statusHistory" : [ {
          "status" : "Review",
          "cts" : 1767954597308,
          "lastModifiedBy" : "685b8a3df073051941d15c1c",
          "description" : "Proxy undeploy"
        }, {
          "status" : "Approved",
          "cts" : 1767954449798,
          "lastModifiedBy" : "685b8a3df073051941d15c1c",
          "description" : " "
        }, {
          "status" : "Review",
          "cts" : 1767954124911,
          "lastModifiedBy" : "685b8a3df073051941d15c1c",
          "description" : "Proxy undeploy"
        }, {
          "status" : "Approved",
          "cts" : 1767953899470,
          "lastModifiedBy" : "685b8a3df073051941d15c1c",
          "description" : " "
        }, {
          "status" : "Review",
          "cts" : 1767953846905,
          "lastModifiedBy" : "685b8a3df073051941d15c1c",
          "description" : "Proxy undeploy"
        }, {
          "status" : "Approved",
          "cts" : 1767953675079,
          "lastModifiedBy" : "685b8a3df073051941d15c1c",
          "description" : " "
        }, {
          "status" : "Review",
          "cts" : 1767953590990,
          "lastModifiedBy" : "685b8a3df073051941d15c1c",
          "description" : "Proxy undeploy"
        }, {
          "status" : "Approved",
          "cts" : 1767953545150,
          "lastModifiedBy" : "685b8a3df073051941d15c1c",
          "description" : " "
        }, {
          "status" : "Review",
          "cts" : 1767953345865,
          "lastModifiedBy" : "685b8a3df073051941d15c1c",
          "description" : "Proxy undeploy"
        }, {
          "status" : "Approved",
          "cts" : 1767953202672,
          "lastModifiedBy" : "685b8a3df073051941d15c1c",
          "description" : " "
        }, {
          "status" : "Review",
          "cts" : 1767953158264,
          "lastModifiedBy" : "685b8a3df073051941d15c1c",
          "description" : "Proxy undeploy"
        }, {
          "status" : "Approved",
          "cts" : 1767952914986,
          "lastModifiedBy" : "685b8a3df073051941d15c1c",
          "description" : " "
        }, {
          "status" : "Review",
          "cts" : 1767952804116,
          "lastModifiedBy" : "685b8a3df073051941d15c1c",
          "description" : "Proxy undeploy"
        }, {
          "status" : "Approved",
          "cts" : 1767952721151,
          "lastModifiedBy" : "685b8a3df073051941d15c1c",
          "description" : " "
        }, {
          "status" : "Review",
          "cts" : 1767952661867,
          "lastModifiedBy" : "685b8a3df073051941d15c1c",
          "description" : "Proxy undeploy"
        }, {
          "status" : "Approved",
          "cts" : 1767952559315,
          "lastModifiedBy" : "685b8a3df073051941d15c1c",
          "description" : " "
        }, {
          "status" : "Draft",
          "cts" : 1767952105628,
          "lastModifiedBy" : "Kiran Kamble",
          "description" : "Created new proxy"
        } ],
        "virtualHostList" : [ ],
        "enableTracing" : false,
        "environmentName" : "",
        "environmentId" : "",
        "selectedVirtualHostName" : "",
        "selectedVirtualHostId" : "",
        "kafkaConnectorId" : "",
        "kafkaTopic" : "",
        "kafkaGroupId" : "",
        "enableLogging" : false,
        "misconfigurationMessages" : [ ],
        "validated" : true,
        "deployed" : false,
        "deleted" : false
      }
    }
  }, {
    "type" : "proxy",
    "collectionName" : "ApiBuilder.Proxy.List",
    "data" : {
      "proxyData" : {
        "id" : "6960939f613749329516d1e7",
        "cts" : 1767936927146,
        "createdUserName" : "divakar v",
        "modifiedUserName" : "Kiran Kamble",
        "mts" : 1767956952875,
        "createdBy" : "63cf749921c7bb55c7368952",
        "modifiedBy" : "685b8a3df073051941d15c1c",
        "taggedTeams" : [ ],
        "proxyId" : "6960939f613749329516d1e6",
        "revision" : 1,
        "name" : "New Workflow 847",
        "description" : "",
        "apiType" : "RESTAPI",
        "apiMethod" : "GET",
        "path" : "/testing-variable-logger/{a}/{b}",
        "pathArray" : [ "testing-variable-logger", "*", "*" ],
        "revisionStatus" : "APPROVED",
        "locked" : true,
        "lockedBy" : "Kiran Kamble",
        "nodeDataHashMap" : {
          "inbound" : {
            "21d40d53-ba0b-4432-a1a7-e612b3704242" : [ "f324c5f3-30d8-43ff-ac35-77653abdec47" ],
            "f324c5f3-30d8-43ff-ac35-77653abdec47" : [ "v1" ]
          },
          "outbound" : {
            "f324c5f3-30d8-43ff-ac35-77653abdec47" : [ "21d40d53-ba0b-4432-a1a7-e612b3704242" ],
            "v1" : [ "f324c5f3-30d8-43ff-ac35-77653abdec47" ]
          },
          "allNeighbours" : [ "21d40d53-ba0b-4432-a1a7-e612b3704242", "v1", "f324c5f3-30d8-43ff-ac35-77653abdec47" ]
        },
        "vertexHashMap" : {
          "21d40d53-ba0b-4432-a1a7-e612b3704242" : {
            "vertexId" : "21d40d53-ba0b-4432-a1a7-e612b3704242",
            "vertexType" : "STOP",
            "name" : "Stop",
            "imported" : false,
            "skipRuntimeVariables" : false,
            "proxyResponse" : {
              "statusCode" : 200,
              "body" : {
                "type" : "JSON"
              }
            }
          },
          "f324c5f3-30d8-43ff-ac35-77653abdec47" : {
            "vertexId" : "f324c5f3-30d8-43ff-ac35-77653abdec47",
            "vertexType" : "LOGGER",
            "name" : "Logging ",
            "description" : "",
            "logData" : {
              "data" : "|{{a}}\n{{b}}",
              "skip" : false
            },
            "imported" : false,
            "skipRuntimeVariables" : false
          },
          "v1" : {
            "vertexId" : "v1",
            "vertexType" : "START",
            "name" : "Request",
            "requestVariables" : [ {
              "name" : "a",
              "reference" : "path-variable",
              "value" : "a",
              "variableDataType" : "INTEGER",
              "active" : true,
              "source" : "path-variable",
              "hide" : false,
              "feelExpression" : false
            }, {
              "name" : "b",
              "reference" : "path-variable",
              "value" : "b",
              "variableDataType" : "INTEGER",
              "active" : true,
              "source" : "path-variable",
              "hide" : false,
              "feelExpression" : false
            } ],
            "mandatoryHeaders" : [ ],
            "mandatoryQueryParams" : [ ],
            "imported" : true,
            "skipRuntimeVariables" : false,
            "securityResponse" : {
              "isEnabled" : false,
              "skip" : false,
              "showActualErrorMessage" : false,
              "continueOnError" : false,
              "errorResponse" : {
                "statusCode" : 400,
                "body" : {
                  "data" : "",
                  "type" : "json"
                }
              }
            }
          }
        },
        "statusHistory" : [ {
          "status" : "Approved",
          "cts" : 1767956948980,
          "lastModifiedBy" : "685b8a3df073051941d15c1c",
          "description" : " "
        }, {
          "status" : "Review",
          "cts" : 1767956929724,
          "lastModifiedBy" : "685b8a3df073051941d15c1c",
          "description" : "Proxy undeploy"
        }, {
          "status" : "Approved",
          "cts" : 1767954004183,
          "lastModifiedBy" : "685b8a3df073051941d15c1c",
          "description" : " "
        }, {
          "status" : "Review",
          "cts" : 1767953985386,
          "lastModifiedBy" : "685b8a3df073051941d15c1c",
          "description" : "Proxy undeploy"
        }, {
          "status" : "Approved",
          "cts" : 1767937184505,
          "lastModifiedBy" : "63cf749921c7bb55c7368952",
          "description" : "qwe"
        }, {
          "status" : "Draft",
          "cts" : 1767936927146,
          "lastModifiedBy" : "divakar v",
          "description" : "Created new proxy"
        } ],
        "virtualHostList" : [ {
          "id" : "66dc0ef2e836d076001b628b",
          "name" : "stage-data",
          "timeStamp" : 1767956952852,
          "deployedBy" : "Kiran Kamble"
        } ],
        "enableTracing" : false,
        "environmentName" : "",
        "environmentId" : "",
        "selectedVirtualHostName" : "",
        "selectedVirtualHostId" : "",
        "kafkaConnectorId" : "",
        "kafkaTopic" : "",
        "kafkaGroupId" : "",
        "enableLogging" : false,
        "misconfigurationMessages" : [ ],
        "validated" : true,
        "deployed" : true,
        "deleted" : false
      }
    }
  }, {
    "type" : "connector",
    "collectionName" : "Connectors.MongoDb.Configuration",
    "data" : {
      "mongoDBConfigurationData" : {
        "id" : "6943e47fd4167432fe664f26",
        "cts" : 1766057087375,
        "createdUserName" : "Deepak Satuluri",
        "modifiedUserName" : "Deepak Satuluri",
        "mts" : 1766061048809,
        "createdBy" : "685a38a166575941216c9c0e",
        "modifiedBy" : "685a38a166575941216c9c0e",
        "name" : "Deepak CloudDB Tagged",
        "description" : "Cloud DB",
        "host" : "cluster0.36fr1.mongodb.net/",
        "scheme" : "mongodb+srv",
        "url" : "mongodb+srv://apiwiz-database:oNyFlrO4XM5AWX8Y@cluster0.36fr1.mongodb.net/",
        "authentication" : {
          "mongoDbAuthType" : "userNamePassword",
          "username" : "apiwiz-database",
          "password" : "oNyFlrO4XM5AWX8Y",
          "authenticationMechanism" : "DEFAULT"
        },
        "ssl" : {
          "sslConnection" : false,
          "tlsAllowInvalidHostnames" : false
        }
      },
      "databaseType" : "MongoDb"
    }
  }, {
    "type" : "sharedFlow",
    "collectionName" : "ApiBuilder.SharedFlows.List",
    "data" : {
      "sharedFlowData" : {
        "id" : "6960d2e5867f997c20008afb",
        "cts" : 1767953125145,
        "createdUserName" : "Kiran Kamble",
        "modifiedUserName" : "Kiran Kamble",
        "mts" : 1767953139475,
        "createdBy" : "685b8a3df073051941d15c1c",
        "modifiedBy" : "685b8a3df073051941d15c1c",
        "taggedTeams" : [ {
          "id" : "6718a20d1e5c001e2fc678c4",
          "name" : "APIwiz_Team"
        }, {
          "id" : "6805e8b4898ae74f4172ef02",
          "name" : "Deepak"
        } ],
        "name" : "TEST_NODE",
        "description" : "",
        "nodeDataHashMap" : {
          "inbound" : {
            "069f2bb8-d03d-4cb1-91a0-cd3b4b3fed78" : [ "v1" ],
            "f8300773-b239-4b41-b9cd-49fe2a085440" : [ "069f2bb8-d03d-4cb1-91a0-cd3b4b3fed78" ]
          },
          "outbound" : {
            "v1" : [ "069f2bb8-d03d-4cb1-91a0-cd3b4b3fed78" ],
            "069f2bb8-d03d-4cb1-91a0-cd3b4b3fed78" : [ "f8300773-b239-4b41-b9cd-49fe2a085440" ]
          },
          "allNeighbours" : [ "f8300773-b239-4b41-b9cd-49fe2a085440", "v1", "069f2bb8-d03d-4cb1-91a0-cd3b4b3fed78" ]
        },
        "vertexHashMap" : {
          "069f2bb8-d03d-4cb1-91a0-cd3b4b3fed78" : {
            "vertexId" : "069f2bb8-d03d-4cb1-91a0-cd3b4b3fed78",
            "vertexType" : "DELAY",
            "name" : "Delay",
            "delayData" : {
              "delayUnit" : "SECONDS",
              "delayAmount" : 4,
              "skip" : false,
              "showActualErrorMessage" : false
            },
            "imported" : false,
            "skipRuntimeVariables" : false
          },
          "v1" : {
            "vertexId" : "v1",
            "vertexType" : "SHARED_FLOW_START",
            "name" : "Input",
            "imported" : false,
            "skipRuntimeVariables" : false
          },
          "f8300773-b239-4b41-b9cd-49fe2a085440" : {
            "vertexId" : "f8300773-b239-4b41-b9cd-49fe2a085440",
            "vertexType" : "SHARED_FLOW_STOP",
            "name" : "Exit",
            "sharedFlowStopData" : {
              "stopNodeAction" : "TERMINATE_WITH_RESPONSE",
              "sharedFlowResponse" : {
                "statusCode" : 200,
                "body" : {
                  "type" : "JSON"
                }
              }
            },
            "imported" : false,
            "skipRuntimeVariables" : false
          }
        },
        "parentWorkflowIds" : [ ],
        "inputVariableList" : [ ],
        "outputVariableList" : [ ],
        "workspaceTenant" : "stage-data",
        "misconfigurationMessages" : [ ],
        "validated" : true
      }
    }
  } ],
  "metadata" : {
    "proxyMetadataDetailsDtoList" : [ {
      "id" : "6960cee9867f997c2000886a",
      "proxyid" : "6960cee9867f997c20008869",
      "name" : "TEST_TBAC_NODES",
      "attachedEnv" : "",
      "attachedSharedFlows" : [ "6960d2e5867f997c20008afb" ],
      "attachedProxies" : [ "6960939f613749329516d1e7" ],
      "attachedConnectors" : [ "6943e47fd4167432fe664f26" ]
    }, {
      "id" : "6960939f613749329516d1e7",
      "proxyid" : "6960939f613749329516d1e6",
      "name" : "New Workflow 847",
      "attachedSharedFlows" : [ ],
      "attachedProxies" : [ ],
      "attachedConnectors" : [ ]
    } ],
    "collectionMetadataDetailsDtoList" : [ ],
    "environmentMetadataDetailsDtoList" : [ {
      "id" : "",
      "name" : ""
    } ],
    "sharedFlowMetadataDetailsDtoList" : [ {
      "id" : "6960d2e5867f997c20008afb",
      "name" : "TEST_NODE",
      "description" : "",
      "attachedSharedFlows" : [ ],
      "attachedProxies" : [ ],
      "attachedConnectors" : [ ]
    } ],
    "connectorMetadataDetailsDtoList" : [ {
      "id" : "6943e47fd4167432fe664f26",
      "name" : "Deepak CloudDB Tagged"
    } ]
  }
}