{
  "cts" : 1767948549868,
  "name" : "TESTING_NODES",
  "exportedBy" : "Kiran Kamble",
  "data" : [ {
    "type" : "proxy",
    "collectionName" : "ApiBuilder.Proxy.List",
    "data" : {
      "proxyData" : {
        "id" : "6960a608613749329516dbb8",
        "cts" : 1767941640043,
        "createdUserName" : "Kiran Kamble",
        "modifiedUserName" : "Kiran Kamble",
        "mts" : 1767948549865,
        "createdBy" : "685b8a3df073051941d15c1c",
        "modifiedBy" : "685b8a3df073051941d15c1c",
        "taggedTeams" : [ ],
        "proxyId" : "6960a608613749329516dbb7",
        "revision" : 1,
        "name" : "TESTING_NODES",
        "description" : "",
        "apiType" : "RESTAPI",
        "apiMethod" : "GET",
        "path" : "/test-node-123",
        "pathArray" : [ "test-node-123" ],
        "revisionStatus" : "REVIEW",
        "locked" : true,
        "lockedBy" : "Kiran Kamble",
        "nodeDataHashMap" : {
          "inbound" : {
            "f2aa4282-335c-49e4-bcb8-cf836ec0d0bd" : [ "v1" ],
            "350b021f-3660-43c7-89c9-e24f2607ec7b" : [ "v1" ],
            "078902eb-f08d-4382-b122-be7aea63808d" : [ "f2aa4282-335c-49e4-bcb8-cf836ec0d0bd", "350b021f-3660-43c7-89c9-e24f2607ec7b" ],
            "6e90519c-4a96-4087-9262-7a7b55e65ad8" : [ "078902eb-f08d-4382-b122-be7aea63808d" ]
          },
          "outbound" : {
            "v1" : [ "f2aa4282-335c-49e4-bcb8-cf836ec0d0bd", "350b021f-3660-43c7-89c9-e24f2607ec7b" ],
            "350b021f-3660-43c7-89c9-e24f2607ec7b" : [ "078902eb-f08d-4382-b122-be7aea63808d" ],
            "f2aa4282-335c-49e4-bcb8-cf836ec0d0bd" : [ "078902eb-f08d-4382-b122-be7aea63808d" ],
            "078902eb-f08d-4382-b122-be7aea63808d" : [ "6e90519c-4a96-4087-9262-7a7b55e65ad8" ]
          },
          "allNeighbours" : [ "6e90519c-4a96-4087-9262-7a7b55e65ad8", "f2aa4282-335c-49e4-bcb8-cf836ec0d0bd", "078902eb-f08d-4382-b122-be7aea63808d", "v1", "350b021f-3660-43c7-89c9-e24f2607ec7b" ]
        },
        "vertexHashMap" : {
          "6e90519c-4a96-4087-9262-7a7b55e65ad8" : {
            "vertexId" : "6e90519c-4a96-4087-9262-7a7b55e65ad8",
            "vertexType" : "STOP",
            "name" : "Stop",
            "imported" : false,
            "skipRuntimeVariables" : false,
            "proxyResponse" : {
              "statusCode" : 200,
              "headers" : {
                "content-type" : "application/json"
              },
              "body" : {
                "data" : "{\n    \"n\": \"mihir\"\n}",
                "type" : "json"
              }
            }
          },
          "f2aa4282-335c-49e4-bcb8-cf836ec0d0bd" : {
            "vertexId" : "f2aa4282-335c-49e4-bcb8-cf836ec0d0bd",
            "vertexType" : "DELAY",
            "name" : "Delay",
            "delayData" : {
              "delayUnit" : "SECONDS",
              "delayAmount" : 10,
              "skip" : false,
              "showActualErrorMessage" : false
            },
            "imported" : false,
            "skipRuntimeVariables" : false
          },
          "v1" : {
            "vertexId" : "v1",
            "vertexType" : "START",
            "name" : "Request",
            "requestVariables" : [ ],
            "mandatoryHeaders" : [ ],
            "mandatoryQueryParams" : [ ],
            "imported" : true,
            "skipRuntimeVariables" : false,
            "securityResponse" : {
              "isEnabled" : false,
              "skip" : false,
              "showActualErrorMessage" : false,
              "continueOnError" : false,
              "errorResponse" : {
                "statusCode" : 400,
                "body" : {
                  "data" : "",
                  "type" : "json"
                }
              }
            }
          },
          "078902eb-f08d-4382-b122-be7aea63808d" : {
            "vertexId" : "078902eb-f08d-4382-b122-be7aea63808d",
            "vertexType" : "OR_NODE",
            "name" : "ibjij",
            "description" : " ojno",
            "imported" : false,
            "skipRuntimeVariables" : false
          },
          "350b021f-3660-43c7-89c9-e24f2607ec7b" : {
            "vertexId" : "350b021f-3660-43c7-89c9-e24f2607ec7b",
            "vertexType" : "DELAY",
            "name" : "Delay",
            "delayData" : {
              "delayUnit" : "SECONDS",
              "delayAmount" : 5,
              "skip" : false,
              "showActualErrorMessage" : false
            },
            "imported" : false,
            "skipRuntimeVariables" : false
          }
        },
        "statusHistory" : [ {
          "status" : "Review",
          "cts" : 1767948515561,
          "lastModifiedBy" : "685b8a3df073051941d15c1c",
          "description" : "Proxy undeploy"
        }, {
          "status" : "Approved",
          "cts" : 1767948457304,
          "lastModifiedBy" : "685b8a3df073051941d15c1c",
          "description" : "ljkn"
        }, {
          "status" : "Review",
          "cts" : 1767948320740,
          "lastModifiedBy" : "685b8a3df073051941d15c1c",
          "description" : "Proxy undeploy"
        }, {
          "status" : "Approved",
          "cts" : 1767948098267,
          "lastModifiedBy" : "685b8a3df073051941d15c1c",
          "description" : " "
        }, {
          "status" : "Review",
          "cts" : 1767948044908,
          "lastModifiedBy" : "685b8a3df073051941d15c1c",
          "description" : "Proxy undeploy"
        }, {
          "status" : "Approved",
          "cts" : 1767948020106,
          "lastModifiedBy" : "685b8a3df073051941d15c1c",
          "description" : " "
        }, {
          "status" : "Review",
          "cts" : 1767947964419,
          "lastModifiedBy" : "685b8a3df073051941d15c1c",
          "description" : "Proxy undeploy"
        }, {
          "status" : "Approved",
          "cts" : 1767947941254,
          "lastModifiedBy" : "685b8a3df073051941d15c1c",
          "description" : " "
        }, {
          "status" : "Review",
          "cts" : 1767947888663,
          "lastModifiedBy" : "685b8a3df073051941d15c1c",
          "description" : "Proxy undeploy"
        }, {
          "status" : "Approved",
          "cts" : 1767947851230,
          "lastModifiedBy" : "685b8a3df073051941d15c1c",
          "description" : " "
        }, {
          "status" : "Review",
          "cts" : 1767947776786,
          "lastModifiedBy" : "685b8a3df073051941d15c1c",
          "description" : "Proxy undeploy"
        }, {
          "status" : "Approved",
          "cts" : 1767947736107,
          "lastModifiedBy" : "685b8a3df073051941d15c1c",
          "description" : " "
        }, {
          "status" : "Review",
          "cts" : 1767947704584,
          "lastModifiedBy" : "685b8a3df073051941d15c1c",
          "description" : "Proxy undeploy"
        }, {
          "status" : "Approved",
          "cts" : 1767947677793,
          "lastModifiedBy" : "685b8a3df073051941d15c1c",
          "description" : " "
        }, {
          "status" : "Review",
          "cts" : 1767947654750,
          "lastModifiedBy" : "685b8a3df073051941d15c1c",
          "description" : "Proxy undeploy"
        }, {
          "status" : "Approved",
          "cts" : 1767947621379,
          "lastModifiedBy" : "685b8a3df073051941d15c1c",
          "description" : " "
        }, {
          "status" : "Review",
          "cts" : 1767947294830,
          "lastModifiedBy" : "685b8a3df073051941d15c1c",
          "description" : "Proxy undeploy"
        }, {
          "status" : "Approved",
          "cts" : 1767947225550,
          "lastModifiedBy" : "685b8a3df073051941d15c1c",
          "description" : " "
        }, {
          "status" : "Review",
          "cts" : 1767947100499,
          "lastModifiedBy" : "685b8a3df073051941d15c1c",
          "description" : "Proxy undeploy"
        }, {
          "status" : "Approved",
          "cts" : 1767943284857,
          "lastModifiedBy" : "685b8a3df073051941d15c1c",
          "description" : "  "
        }, {
          "status" : "Review",
          "cts" : 1767943126502,
          "lastModifiedBy" : "685b8a3df073051941d15c1c",
          "description" : "Proxy undeploy"
        }, {
          "status" : "Approved",
          "cts" : 1767943012829,
          "lastModifiedBy" : "685b8a3df073051941d15c1c",
          "description" : " "
        }, {
          "status" : "Review",
          "cts" : 1767942690270,
          "lastModifiedBy" : "685b8a3df073051941d15c1c",
          "description" : "Proxy undeploy"
        }, {
          "status" : "Approved",
          "cts" : 1767942638983,
          "lastModifiedBy" : "685b8a3df073051941d15c1c",
          "description" : " "
        }, {
          "status" : "Review",
          "cts" : 1767942611869,
          "lastModifiedBy" : "685b8a3df073051941d15c1c",
          "description" : "Proxy undeploy"
        }, {
          "status" : "Approved",
          "cts" : 1767942452589,
          "lastModifiedBy" : "685b8a3df073051941d15c1c",
          "description" : " "
        }, {
          "status" : "Review",
          "cts" : 1767942436284,
          "lastModifiedBy" : "685b8a3df073051941d15c1c",
          "description" : "Proxy undeploy"
        }, {
          "status" : "Approved",
          "cts" : 1767942131071,
          "lastModifiedBy" : "685b8a3df073051941d15c1c",
          "description" : " "
        }, {
          "status" : "Draft",
          "cts" : 1767941640043,
          "lastModifiedBy" : "Kiran Kamble",
          "description" : "Created new proxy"
        } ],
        "virtualHostList" : [ ],
        "enableTracing" : false,
        "environmentName" : "",
        "environmentId" : "",
        "selectedVirtualHostName" : "",
        "selectedVirtualHostId" : "",
        "kafkaConnectorId" : "",
        "kafkaTopic" : "",
        "kafkaGroupId" : "",
        "enableLogging" : false,
        "misconfigurationMessages" : [ ],
        "validated" : true,
        "deleted" : false,
        "deployed" : false
      }
    }
  } ],
  "metadata" : {
    "proxyMetadataDetailsDtoList" : [ {
      "id" : "6960a608613749329516dbb8",
      "proxyid" : "6960a608613749329516dbb7",
      "name" : "TESTING_NODES",
      "attachedEnv" : "",
      "attachedSharedFlows" : [ ],
      "attachedProxies" : [ ],
      "attachedConnectors" : [ ]
    } ],
    "collectionMetadataDetailsDtoList" : [ ],
    "environmentMetadataDetailsDtoList" : [ {
      "id" : "",
      "name" : ""
    } ],
    "sharedFlowMetadataDetailsDtoList" : [ ],
    "connectorMetadataDetailsDtoList" : [ ]
  }
}