{
  "cts" : 1764839877807,
  "name" : "New Workflow 227",
  "exportedBy" : "Sujith Kumar",
  "data" : [ {
    "type" : "proxy",
    "collectionName" : "ApiBuilder.Proxy.List",
    "data" : {
      "proxyData" : {
        "id" : "693151c506e05678e39a0e45",
        "cts" : 1764839877775,
        "createdUserName" : "Sujith Kumar",
        "modifiedUserName" : "Sujith Kumar",
        "mts" : 1764839877775,
        "createdBy" : "67a0969408a0e559a5309912",
        "modifiedBy" : "67a0969408a0e559a5309912",
        "proxyId" : "693151c506e05678e39a0e44",
        "revision" : 1,
        "name" : "New Workflow 227",
        "description" : "",
        "apiType" : "RESTAPI",
        "apiMethod" : "GET",
        "path" : "/",
        "pathArray" : [ ],
        "revisionStatus" : "DRAFT",
        "locked" : true,
        "lockedBy" : "Sujith Kumar",
        "nodeDataHashMap" : {
          "inbound" : {
            "15abd5cb-6fa6-4fc7-8f90-409ab93d0eee" : [ "v1" ]
          },
          "outbound" : {
            "v1" : [ "15abd5cb-6fa6-4fc7-8f90-409ab93d0eee" ]
          },
          "allNeighbours" : [ "v1", "15abd5cb-6fa6-4fc7-8f90-409ab93d0eee" ]
        },
        "vertexHashMap" : {
          "v1" : {
            "vertexId" : "v1",
            "vertexType" : "START",
            "name" : "Request",
            "requestVariables" : [ ],
            "mandatoryHeaders" : [ ],
            "mandatoryQueryParams" : [ ],
            "imported" : true,
            "skipRuntimeVariables" : false,
            "securityResponse" : {
              "isEnabled" : false,
              "skip" : false,
              "showActualErrorMessage" : false,
              "continueOnError" : false,
              "errorResponse" : {
                "statusCode" : 400,
                "body" : {
                  "data" : "",
                  "type" : "json"
                }
              }
            }
          },
          "15abd5cb-6fa6-4fc7-8f90-409ab93d0eee" : {
            "vertexId" : "15abd5cb-6fa6-4fc7-8f90-409ab93d0eee",
            "vertexType" : "STOP",
            "name" : "Stop",
            "imported" : false,
            "skipRuntimeVariables" : false,
            "proxyResponse" : {
              "statusCode" : 200,
              "body" : {
                "type" : "JSON"
              }
            }
          }
        },
        "statusHistory" : [ {
          "status" : "Draft",
          "cts" : 1764839877775,
          "lastModifiedBy" : "Sujith Kumar",
          "description" : "Created new proxy"
        } ],
        "enableTracing" : false,
        "environmentName" : "",
        "environmentId" : "",
        "selectedVirtualHostName" : "",
        "selectedVirtualHostId" : "",
        "kafkaConnectorId" : "",
        "kafkaTopic" : "",
        "kafkaGroupId" : "",
        "enableLogging" : false,
        "deleted" : false,
        "deployed" : false
      }
    }
  } ],
  "metadata" : {
    "proxyMetadataDetailsDtoList" : [ {
      "id" : "693151c506e05678e39a0e45",
      "proxyid" : "693151c506e05678e39a0e44",
      "name" : "New Workflow 227",
      "attachedEnv" : "",
      "attachedSharedFlows" : [ ],
      "attachedProxies" : [ ],
      "attachedConnectors" : [ ]
    } ],
    "collectionMetadataDetailsDtoList" : [ ],
    "environmentMetadataDetailsDtoList" : [ {
      "id" : "",
      "name" : ""
    } ],
    "sharedFlowMetadataDetailsDtoList" : [ ],
    "connectorMetadataDetailsDtoList" : [ ]
  }
}